{
	"name": "mocha-reporter-sonarqube",
	"image": "mcr.microsoft.com/devcontainers/typescript-node:4-22-bookworm@sha256:c4b7b87ff47b18de2116eb0b0aab7f621a8c5639eaae65e8e123a62450c7837e",
	"features": {
		"ghcr.io/devcontainers/features/github-cli:1": {}
	},
	"postCreateCommand": "npm install",
	"customizations": {
		"vscode": {
			"extensions": [
				"dlech.chmod",
				"GitHub.copilot",
				"esbenp.prettier-vscode",
				"zhiayang.tabindentspacealign",
				"GitHub.copilot-chat",
				"github.vscode-github-actions"
			]
		}
	}
}
